<?xml version="1.0" encoding="utf-8"?>
<SoundBanksInfo Platform="Windows" BasePlatform="Windows" SchemaVersion="16" SoundBankVersion="150">
	<SoundBanks>
		<SoundBank Id="577502352" Type="Event" GUID="{5488BE8E-DDB8-4BBA-8032-D59549B43C49}" Language="English(US)" Hash="{33695D9A-65B9-64B5-847D-A8872C745C3E}">
			<ObjectPath>VO_Blaise_Gameplay_Run</ObjectPath>
			<ShortName>VO_Blaise_Gameplay_Run</ShortName>
			<Path>Event/English(US)/VO_Blaise_Gameplay_Run.bnk</Path>
			<Media>
				<File Id="820038228" Language="English(US)" Streaming="false" Location="Loose">
					<ShortName>VO_Blaise_Gameplay\VO_Blaise_Gameplay_Run.wav</ShortName>
					<Path>Media/English(US)/820038228.wem</Path>
					<CachePath>Voices/English(US)/VO_Blaise_Gameplay/VO_Blaise_Gameplay_Run_818F3B66.wem</CachePath>
				</File>
			</Media>
			<Events>
				<Event Id="577502352" Name="VO_Blaise_Gameplay_Run" ObjectPath="\Events\VO\VO_Blaise_Gameplay\VO_Blaise_Gameplay_Run" GUID="{5488BE8E-DDB8-4BBA-8032-D59549B43C49}" DurationType="OneShot" DurationMin="1.3066666" DurationMax="1.3066666">
					<MediaRefs>
						<MediaRef Id="820038228"/>
					</MediaRefs>
				</Event>
			</Events>
			<GameParameters>
				<GameParameter Id="1474581964" Name="RTPC_Elevation" ObjectPath="\Game Parameters\RTPC_Persistent\RTPC_Elevation" GUID="{B7917ADE-F1CD-4C71-BAE5-1C0713B8B931}"/>
				<GameParameter Id="3972935021" Name="RTPC_Azimuth" ObjectPath="\Game Parameters\RTPC_Persistent\RTPC_Azimuth" GUID="{771130CB-E8A2-4560-ADCA-06985A29C132}"/>
			</GameParameters>
		</SoundBank>
	</SoundBanks>
	<FileHash>{93FE225E-9B75-1A25-F1A4-80FD2F20F7DD}</FileHash>
</SoundBanksInfo>
