{
 "SoundBanksInfo": {
  "Platform": "Windows",
  "BasePlatform": "Windows",
  "SchemaVersion": "16",
  "SoundBankVersion": "150",
  "SoundBanks": [
   {
    "Id": "1392877436",
    "Type": "Event",
    "GUID": "{42B1E8D9-E28F-4D35-A73E-F9E0E7104D8F}",
    "Language": "English(US)",
    "Hash": "{3B473909-231B-FCB0-6427-317567779EA1}",
    "ObjectPath": "VO_Diana_Gameplay_02",
    "ShortName": "VO_Diana_Gameplay_02",
    "Path": "Event/English(US)/VO_Diana_Gameplay_02.bnk",
    "Media": [
     {
      "Id": "443785590",
      "Language": "English(US)",
      "Streaming": "false",
      "Location": "Loose",
      "ShortName": "VO_Diana_Gameplay\\VO_Diana_Gameplay_02.wav",
      "Path": "Media/English(US)/443785590.wem",
      "CachePath": "Voices/English(US)/VO_Diana_Gameplay/VO_Diana_Gameplay_02_818F3B66.wem"
     }
    ],
    "Events": [
     {
      "Id": "1392877436",
      "Name": "VO_Diana_Gameplay_02",
      "ObjectPath": "\\Events\\VO\\VO_Diana_Gameplay\\VO_Diana_Gameplay_02",
      "GUID": "{42B1E8D9-E28F-4D35-A73E-F9E0E7104D8F}",
      "DurationType": "OneShot",
      "DurationMin": "1",
      "DurationMax": "1",
      "MediaRefs": [
       {
        "Id": "443785590"
       }
      ]
     }
    ],
    "GameParameters": [
     {
      "Id": "1474581964",
      "Name": "RTPC_Elevation",
      "ObjectPath": "\\Game Parameters\\RTPC_Persistent\\RTPC_Elevation",
      "GUID": "{B7917ADE-F1CD-4C71-BAE5-1C0713B8B931}"
     },
     {
      "Id": "3972935021",
      "Name": "RTPC_Azimuth",
      "ObjectPath": "\\Game Parameters\\RTPC_Persistent\\RTPC_Azimuth",
      "GUID": "{771130CB-E8A2-4560-ADCA-06985A29C132}"
     }
    ]
   }
  ],
  "FileHash": "{9BE9DEEB-7456-01CF-766B-8F1960602DDE}"
 }
}